pyref_staging-0.2.1.dist-info/METADATA
pyref_staging-0.2.1.dist-info/WHEEL
pyref_staging-0.2.1.dist-info/licenses/LICENSE
pyref/masking.py
pyref/image.py
pyref/types.py
pyref/utils/__init__.py
pyref/widgets.py
pyref/exceptions.py
pyref/__init__.py
pyref/runfile.py
pyref/fitting/__init__.py
pyref/fitting/logp.py
pyref/loader.py
pyref/pyref.cpython-37m-x86_64-linux-gnu.so
pyref_staging-0.2.1.dist-info/RECORD
