Metadata-Version: 2.4
Name: pyref_staging
Version: 0.2.1
Classifier: Programming Language :: Rust
Classifier: Programming Language :: Python :: Implementation :: CPython
Classifier: Programming Language :: Python :: Implementation :: PyPy
Classifier: Intended Audience :: Science/Research
Classifier: Topic :: Scientific/Engineering :: Physics
Requires-Dist: numpy
Requires-Dist: numba
Requires-Dist: pandas
Requires-Dist: polars
Requires-Dist: matplotlib
Requires-Dist: jupyter
Requires-Dist: scipy
Requires-Dist: scikit-learn
Requires-Dist: ipywidgets >=8.1.3
Requires-Dist: refnx >=0.1.47
Requires-Dist: fastparquet >=2024.5.0
Requires-Dist: pyarrow >=17.0.0
Requires-Dist: scikit-image >=0.24.0
Requires-Dist: maturin >=1.7.1
Requires-Dist: ipympl >=0.9.4
Requires-Dist: hvplot >=0.11.2
License-File: LICENSE
Summary: Blazingly fast X-ray reflectivity data analysis package
Keywords: X-ray,reflectivity,data,analysis
Author: Harlan Heilman Harlan.Heilman@wsu.edu
Author-email: Harlan <Harlan.Heilman@wsu.edu>
License: GPL-3.0
Requires-Python: >=3.12
Project-URL: Source Code, https://github.com/WSU-Carbon-Lab/pyref
